sendpost_python_sdk/__init__.py
sendpost_python_sdk/api_client.py
sendpost_python_sdk/api_response.py
sendpost_python_sdk/configuration.py
sendpost_python_sdk/exceptions.py
sendpost_python_sdk/py.typed
sendpost_python_sdk/rest.py
sendpost_python_sdk/api/__init__.py
sendpost_python_sdk/api/domain_api.py
sendpost_python_sdk/api/email_api.py
sendpost_python_sdk/api/ip_api.py
sendpost_python_sdk/api/ip_pools_api.py
sendpost_python_sdk/api/message_api.py
sendpost_python_sdk/api/stats_a_api.py
sendpost_python_sdk/api/stats_api.py
sendpost_python_sdk/api/sub_account_api.py
sendpost_python_sdk/api/suppression_api.py
sendpost_python_sdk/api/webhook_api.py
sendpost_python_sdk/models/__init__.py
sendpost_python_sdk/models/account_stats.py
sendpost_python_sdk/models/account_stats_stat.py
sendpost_python_sdk/models/aggregate_stat.py
sendpost_python_sdk/models/aggregate_stats.py
sendpost_python_sdk/models/aggregated_email_stats.py
sendpost_python_sdk/models/attachment.py
sendpost_python_sdk/models/auto_warmup_plan.py
sendpost_python_sdk/models/copy_to.py
sendpost_python_sdk/models/create_domain_request.py
sendpost_python_sdk/models/create_sub_account_request.py
sendpost_python_sdk/models/create_suppression_request.py
sendpost_python_sdk/models/create_suppression_request_hard_bounce_inner.py
sendpost_python_sdk/models/create_suppression_request_manual_inner.py
sendpost_python_sdk/models/create_suppression_request_spam_complaint_inner.py
sendpost_python_sdk/models/create_suppression_request_unsubscribe_inner.py
sendpost_python_sdk/models/create_webhook_request.py
sendpost_python_sdk/models/delete_response.py
sendpost_python_sdk/models/delete_sub_account_response.py
sendpost_python_sdk/models/delete_suppression200_response_inner.py
sendpost_python_sdk/models/delete_suppression_request.py
sendpost_python_sdk/models/delete_webhook_response.py
sendpost_python_sdk/models/device.py
sendpost_python_sdk/models/domain.py
sendpost_python_sdk/models/domain_dkim.py
sendpost_python_sdk-2.0.1.dist-info/licenses/LICENSE
sendpost_python_sdk-2.0.1.dist-info/METADATA
sendpost_python_sdk-2.0.1.dist-info/WHEEL
sendpost_python_sdk-2.0.1.dist-info/top_level.txt
sendpost_python_sdk-2.0.1.dist-info/RECORD
